custom_color_palette/__init__.py
custom_color_palette/creates_custom_palette.py
custom_color_palette-3.1.dist-info/LICENSE
custom_color_palette-3.1.dist-info/METADATA
custom_color_palette-3.1.dist-info/WHEEL
custom_color_palette-3.1.dist-info/top_level.txt
custom_color_palette-3.1.dist-info/RECORD
