Metadata-Version: 2.1
Name: custom-color-palette
Version: 3.1
Summary: Creates a custom color palette
Home-page: https://github.com/joaohenry23/custom_color_palette
Author: Joao Henry Huamán Chinchay
Author-email: joaohenry23@gmail.com
License: BSD 3-Clause
Platform: UNKNOWN
Classifier: Programming Language :: Python :: 2
Classifier: Programming Language :: Python :: 3
Classifier: License :: OSI Approved :: BSD License
Classifier: Operating System :: OS Independent
Requires-Python: >=2.7
Requires-Dist: numpy
Requires-Dist: matplotlib
